restate/__init__.py
restate/_internal.cpython-314-x86_64-linux-gnu.so
restate/asyncio.py
restate/aws_lambda.py
restate/client.py
restate/client_types.py
restate/context.py
restate/context_managers.py
restate/discovery.py
restate/endpoint.py
restate/exceptions.py
restate/ext/__init__.py
restate/ext/adk/__init__.py
restate/ext/adk/plugin.py
restate/ext/adk/session.py
restate/ext/openai/__init__.py
restate/ext/openai/functions.py
restate/ext/openai/models.py
restate/ext/openai/runner_wrapper.py
restate/ext/openai/session.py
restate/ext/pydantic/__init__.py
restate/ext/pydantic/_agent.py
restate/ext/pydantic/_model.py
restate/ext/pydantic/_serde.py
restate/ext/pydantic/_toolset.py
restate/ext/pydantic/_utils.py
restate/ext/turnstile.py
restate/extensions.py
restate/handler.py
restate/harness.py
restate/logging.py
restate/object.py
restate/py.typed
restate/retry_policy.py
restate/serde.py
restate/server.py
restate/server_context.py
restate/server_types.py
restate/service.py
restate/types.py
restate/vm.py
restate/workflow.py
restate_sdk-0.14.0.dist-info/METADATA
restate_sdk-0.14.0.dist-info/WHEEL
restate_sdk-0.14.0.dist-info/licenses/LICENSE
restate_sdk-0.14.0.dist-info/RECORD
