Metadata-Version: 2.4
Name: restate-sdk
Version: 0.14.0
Classifier: Programming Language :: Rust
Classifier: Programming Language :: Python :: Implementation :: CPython
Classifier: Topic :: Software Development :: Libraries :: Application Frameworks
Requires-Dist: google-adk>=1.20.0 ; extra == 'adk'
Requires-Dist: httpx[http2] ; extra == 'client'
Requires-Dist: testcontainers ; extra == 'harness'
Requires-Dist: hypercorn ; extra == 'harness'
Requires-Dist: httpx ; extra == 'harness'
Requires-Dist: mypy>=1.11.2 ; extra == 'lint'
Requires-Dist: pyright>=1.1.390 ; extra == 'lint'
Requires-Dist: ruff>=0.6.9 ; extra == 'lint'
Requires-Dist: openai-agents>=0.6.1 ; extra == 'openai'
Requires-Dist: pydantic-ai-slim>=1.35.0 ; extra == 'pydantic-ai'
Requires-Dist: dacite ; extra == 'serde'
Requires-Dist: pydantic ; extra == 'serde'
Requires-Dist: msgspec ; extra == 'serde'
Requires-Dist: pytest ; extra == 'test'
Requires-Dist: hypercorn ; extra == 'test'
Requires-Dist: anyio ; extra == 'test'
Provides-Extra: adk
Provides-Extra: client
Provides-Extra: harness
Provides-Extra: lint
Provides-Extra: openai
Provides-Extra: pydantic_ai
Provides-Extra: serde
Provides-Extra: test
License-File: LICENSE
Summary: A Python SDK for Restate
Author-email: Restate Developers <dev@restate.dev>
License-Expression: MIT
Requires-Python: >=3.10
Project-URL: Bug Tracker, https://github.com/restatedev/sdk-python/issues
Project-URL: Documentation, https://docs.restate.dev
Project-URL: Homepage, https://restate.dev
Project-URL: Source, https://github.com/restatedev/sdk-python
